ft_fibonacci/__init__.py
ft_fibonacci/app.py
ft_fibonacci-1.0.0.dist-info/LICENSE
ft_fibonacci-1.0.0.dist-info/METADATA
ft_fibonacci-1.0.0.dist-info/WHEEL
ft_fibonacci-1.0.0.dist-info/top_level.txt
ft_fibonacci-1.0.0.dist-info/RECORD
