Metadata-Version: 2.1
Name: ft-fibonacci
Version: 1.0.0
Summary: A simple test package to calculate Fibonacci Sequence through a recursive approach
Home-page: https://github.com/fahadtaimur
Author: Fahad Taimur
Author-email: fahadtaimur@protonmail.com
License: MIT
Classifier: Programming Language :: Python :: 3
Classifier: Operating System :: OS Independent
License-File: LICENSE
